README.md
setup.py
cip/__init__.py
cip/cip.py
cip.egg-info/PKG-INFO
cip.egg-info/SOURCES.txt
cip.egg-info/dependency_links.txt
cip.egg-info/top_level.txt