Metadata-Version: 2.1
Name: cip
Version: 1.6
Summary: c/c++ install package
Home-page: https://github.com/jdhxyy/cip
Author: jdh99
Author-email: jdh821@163.com
License: UNKNOWN
Platform: UNKNOWN
